{
    "id": "coater1usa",
    "attributes": {
        "type": "Service_coa1",
        "actions": {
            "coating": {
                "properties": {
                    "type": "operation",
                    "command": "coat_1",
                    "cost": 5,
                    "parameters": [
                        "Material - w"
                    ],
                    "requirements": {
                        "positive": [
                            "w.deposited:true",
                            "w.coated:false",
                            "status:available"
                        ]
                    },
                    "effects": {
                        "added": [
                            "w.coated:true"
                        ],
                        "deleted": [
                            "w.coated:false"
                        ]
                    }
                }
            }
        }
    },
    "features": {
        "status":{
            "properties": {
                "value": "available"
            }
        }
    }
}